adi_distributions/Binomialdistribution.py
adi_distributions/Gaussiandistribution.py
adi_distributions/Generaldistribution.py
adi_distributions/__init__.py
adi_distributions-1.2.dist-info/METADATA
adi_distributions-1.2.dist-info/WHEEL
adi_distributions-1.2.dist-info/top_level.txt
adi_distributions-1.2.dist-info/RECORD
