Metadata-Version: 2.1
Name: adi_distributions
Version: 1.2
Summary: Gaussian and Binomial distributions
Author: Adithya Chintala
